{
    "data": [
        {
            "Time": "2023-03-01",
            "value": 172.47000122070312
        },
        {
            "Time": "2023-03-02",
            "value": 174.36000061035156
        },
        {
            "Time": "2023-03-03",
            "value": 178.02000427246094
        },
        {
            "Time": "2023-03-06",
            "value": 178.8300018310547
        },
        {
            "Time": "2023-03-07",
            "value": 176.77999877929688
        },
        {
            "Time": "2023-03-08",
            "value": 177.1199951171875
        },
        {
            "Time": "2023-03-09",
            "value": 173.17999267578125
        },
        {
            "Time": "2023-03-10",
            "value": 170.7100067138672
        },
        {
            "Time": "2023-03-13",
            "value": 171.1300048828125
        },
        {
            "Time": "2023-03-14",
            "value": 175.83999633789062
        },
        {
            "Time": "2023-03-15",
            "value": 178.47999572753906
        },
        {
            "Time": "2023-03-16",
            "value": 183.42999267578125
        },
        {
            "Time": "2023-03-17",
            "value": 182.55999755859375
        },
        {
            "Time": "2023-03-20",
            "value": 183.44000244140625
        },
        {
            "Time": "2023-03-21",
            "value": 187.92999267578125
        },
        {
            "Time": "2023-03-22",
            "value": 184.8800048828125
        },
        {
            "Time": "2023-03-23",
            "value": 188.27000427246097
        },
        {
            "Time": "2023-03-24",
            "value": 188.77000427246097
        },
        {
            "Time": "2023-03-27",
            "value": 186.7400054931641
        },
        {
            "Time": "2023-03-28",
            "value": 184.83999633789065
        },
        {
            "Time": "2023-03-29",
            "value": 187.02999877929688
        },
        {
            "Time": "2023-03-30",
            "value": 187.6300048828125
        },
        {
            "Time": "2023-03-31",
            "value": 191.52999877929688
        }
    ]
}