{
    "data": [
        {
            "Time": "2023-03-01",
            "value": 54.61903381347656
        },
        {
            "Time": "2023-03-02",
            "value": 55.85994338989258
        },
        {
            "Time": "2023-03-03",
            "value": 56.326454162597656
        },
        {
            "Time": "2023-03-06",
            "value": 56.07453918457031
        },
        {
            "Time": "2023-03-07",
            "value": 54.62835693359375
        },
        {
            "Time": "2023-03-08",
            "value": 55.07620620727539
        },
        {
            "Time": "2023-03-09",
            "value": 54.416725158691406
        },
        {
            "Time": "2023-03-10",
            "value": 53.0977668762207
        },
        {
            "Time": "2023-03-13",
            "value": 53.76667022705078
        },
        {
            "Time": "2023-03-14",
            "value": 55.13273620605469
        },
        {
            "Time": "2023-03-15",
            "value": 55.226951599121094
        },
        {
            "Time": "2023-03-16",
            "value": 55.75453186035156
        },
        {
            "Time": "2023-03-17",
            "value": 55.14215850830078
        },
        {
            "Time": "2023-03-20",
            "value": 55.886436462402344
        },
        {
            "Time": "2023-03-21",
            "value": 55.14215850830078
        },
        {
            "Time": "2023-03-22",
            "value": 53.82320022583008
        },
        {
            "Time": "2023-03-23",
            "value": 53.45576858520508
        },
        {
            "Time": "2023-03-24",
            "value": 55.377689361572266
        },
        {
            "Time": "2023-03-27",
            "value": 55.7922248840332
        },
        {
            "Time": "2023-03-28",
            "value": 56.41401672363281
        },
        {
            "Time": "2023-03-29",
            "value": 57.78950881958008
        },
        {
            "Time": "2023-03-30",
            "value": 58.28883743286133
        },
        {
            "Time": "2023-03-31",
            "value": 58.835262298583984
        }
    ]
}